{"Commands":[{"CommandId":1,"Collection":"linux","Description":"Show system and kernel","CommandText":"uname -a","Tags":[{"Name":"bash"}],"CreatedAtUtc":"2024-02-21T22:47:40.5941485Z","SearchableText":"Show system and kernel uname -a bash linux","Size":42,"Id":"linux_1","HasId":true},{"CommandId":2,"Collection":"linux","Description":"Show distri­bution","CommandText":"head -n1 /etc/issue","Tags":[{"Name":"bash"}],"CreatedAtUtc":"2024-02-21T22:47:40.5942368Z","SearchableText":"Show distri­bution head -n1 /etc/issue bash linux","Size":50,"Id":"linux_2","HasId":true},{"CommandId":3,"Collection":"linux","Description":"Show mounted filesy­stems","CommandText":"mount","Tags":[{"Name":"bash"}],"CreatedAtUtc":"2024-02-21T22:47:40.5942408Z","SearchableText":"Show mounted filesy­stems mount bash linux","Size":43,"Id":"linux_3","HasId":true},{"CommandId":4,"Collection":"linux","Description":"Show system date","CommandText":"date","Tags":[{"Name":"bash"}],"CreatedAtUtc":"2024-02-21T22:47:40.5942427Z","SearchableText":"Show system date date bash linux","Size":32,"Id":"linux_4","HasId":true},{"CommandId":5,"Collection":"linux","Description":"Show uptime","CommandText":"uptime","Tags":[{"Name":"bash"}],"CreatedAtUtc":"2024-02-21T22:47:40.5942442Z","SearchableText":"Show uptime uptime bash linux","Size":29,"Id":"linux_5","HasId":true},{"CommandId":6,"Collection":"linux","Description":"Show your username","CommandText":"whoami","Tags":[{"Name":"bash"}],"CreatedAtUtc":"2024-02-21T22:47:40.5942463Z","SearchableText":"Show your username whoami bash linux","Size":36,"Id":"linux_6","HasId":true},{"CommandId":7,"Collection":"linux","Description":"Show manual for command","CommandText":"man command","Tags":[{"Name":"bash"}],"CreatedAtUtc":"2024-02-21T22:47:40.5942481Z","SearchableText":"Show manual for command man command bash linux","Size":46,"Id":"linux_7","HasId":true},{"CommandId":8,"Collection":"linux","Description":"Stop current command","CommandText":"CTRL-c","Tags":[{"Name":"bash"}],"CreatedAtUtc":"2024-02-21T22:47:40.5942497Z","SearchableText":"Stop current command CTRL-c bash linux","Size":38,"Id":"linux_8","HasId":true},{"CommandId":9,"Collection":"linux","Description":"Sleep program","CommandText":"CTRL-z","Tags":[{"Name":"bash"}],"CreatedAtUtc":"2024-02-21T22:47:40.5942514Z","SearchableText":"Sleep program CTRL-z bash linux","Size":31,"Id":"linux_9","HasId":true},{"CommandId":10,"Collection":"linux","Description":"Go to start of line","CommandText":"CTRL-a","Tags":[{"Name":"bash"}],"CreatedAtUtc":"2024-02-21T22:47:40.5942533Z","SearchableText":"Go to start of line CTRL-a bash linux","Size":37,"Id":"linux_10","HasId":true},{"CommandId":11,"Collection":"linux","Description":"Go to end of line","CommandText":"CTRL-e","Tags":[{"Name":"bash"}],"CreatedAtUtc":"2024-02-21T22:47:40.5942549Z","SearchableText":"Go to end of line CTRL-e bash linux","Size":35,"Id":"linux_11","HasId":true},{"CommandId":12,"Collection":"linux","Description":"Cut from start of line","CommandText":"CTRL-u","Tags":[{"Name":"bash"}],"CreatedAtUtc":"2024-02-21T22:47:40.5942565Z","SearchableText":"Cut from start of line CTRL-u bash linux","Size":40,"Id":"linux_12","HasId":true},{"CommandId":13,"Collection":"linux","Description":"Cut to end of line","CommandText":"CTRL-k","Tags":[{"Name":"bash"}],"CreatedAtUtc":"2024-02-21T22:47:40.5942582Z","SearchableText":"Cut to end of line CTRL-k bash linux","Size":36,"Id":"linux_13","HasId":true},{"CommandId":14,"Collection":"linux","Description":"Search history","CommandText":"CTRL-r","Tags":[{"Name":"bash"}],"CreatedAtUtc":"2024-02-21T22:47:40.5942597Z","SearchableText":"Search history CTRL-r bash linux","Size":32,"Id":"linux_14","HasId":true},{"CommandId":15,"Collection":"linux","Description":"Repeat last command","CommandText":"!!","Tags":[{"Name":"bash"}],"CreatedAtUtc":"2024-02-21T22:47:40.5942612Z","SearchableText":"Repeat last command !! bash linux","Size":33,"Id":"linux_15","HasId":true},{"CommandId":16,"Collection":"linux","Description":"Run last command starting with abc","CommandText":"!abc","Tags":[{"Name":"bash"}],"CreatedAtUtc":"2024-02-21T22:47:40.5942661Z","SearchableText":"Run last command starting with abc !abc bash linux","Size":50,"Id":"linux_16","HasId":true},{"CommandId":17,"Collection":"linux","Description":"Print last command starting with abc","CommandText":"!abc:p","Tags":[{"Name":"bash"}],"CreatedAtUtc":"2024-02-21T22:47:40.5942681Z","SearchableText":"Print last command starting with abc !abc:p bash linux","Size":54,"Id":"linux_17","HasId":true},{"CommandId":18,"Collection":"linux","Description":"Last argument of previous command","CommandText":"!$","Tags":[{"Name":"bash"}],"CreatedAtUtc":"2024-02-21T22:47:40.5942701Z","SearchableText":"Last argument of previous command !$ bash linux","Size":47,"Id":"linux_18","HasId":true},{"CommandId":19,"Collection":"linux","Description":"Last argument of previous command","CommandText":"ALT-.","Tags":[{"Name":"bash"}],"CreatedAtUtc":"2024-02-21T22:47:40.5942721Z","SearchableText":"Last argument of previous command ALT-. bash linux","Size":50,"Id":"linux_19","HasId":true},{"CommandId":20,"Collection":"linux","Description":"All arguments of previous command","CommandText":"!*","Tags":[{"Name":"bash"}],"CreatedAtUtc":"2024-02-21T22:47:40.5942739Z","SearchableText":"All arguments of previous command !* bash linux","Size":47,"Id":"linux_20","HasId":true},{"CommandId":21,"Collection":"linux","Description":"Run previous command, replacing abc with 123","CommandText":"^abc^123","Tags":[{"Name":"bash"}],"CreatedAtUtc":"2024-02-21T22:47:40.594276Z","SearchableText":"Run previous command, replacing abc with 123 ^abc^123 bash linux","Size":64,"Id":"linux_21","HasId":true},{"CommandId":22,"Collection":"linux","Description":"Show enviro­nment variables","CommandText":"env","Tags":[{"Name":"bash"}],"CreatedAtUtc":"2024-02-21T22:47:40.5942777Z","SearchableText":"Show enviro­nment variables env bash linux","Size":43,"Id":"linux_22","HasId":true},{"CommandId":23,"Collection":"linux","Description":"Output value of $NAME environment variable","CommandText":"echo $NAME","Tags":[{"Name":"bash"}],"CreatedAtUtc":"2024-02-21T22:47:40.59428Z","SearchableText":"Output value of $NAME environment variable echo $NAME bash linux","Size":64,"Id":"linux_23","HasId":true},{"CommandId":24,"Collection":"linux","Description":"Set $NAME variable to value","CommandText":"export NAME=value","Tags":[{"Name":"bash"}],"CreatedAtUtc":"2024-02-21T22:47:40.594282Z","SearchableText":"Set $NAME variable to value export NAME=value bash linux","Size":56,"Id":"linux_24","HasId":true},{"CommandId":25,"Collection":"linux","Description":"Executable search path","CommandText":"$PATH","Tags":[{"Name":"bash"}],"CreatedAtUtc":"2024-02-21T22:47:40.5942836Z","SearchableText":"Executable search path $PATH bash linux","Size":39,"Id":"linux_25","HasId":true},{"CommandId":26,"Collection":"linux","Description":"Home directory","CommandText":"$HOME","Tags":[{"Name":"bash"}],"CreatedAtUtc":"2024-02-21T22:47:40.5942852Z","SearchableText":"Home directory $HOME bash linux","Size":31,"Id":"linux_26","HasId":true},{"CommandId":27,"Collection":"linux","Description":"Current shell","CommandText":"$SHELL","Tags":[{"Name":"bash"}],"CreatedAtUtc":"2024-02-21T22:47:40.5942866Z","SearchableText":"Current shell $SHELL bash linux","Size":31,"Id":"linux_27","HasId":true},{"CommandId":28,"Collection":"linux","Description":"Input of cmd from file","CommandText":"cmd < file","Tags":[{"Name":"io"}],"CreatedAtUtc":"2024-02-21T22:47:40.5942885Z","SearchableText":"Input of cmd from file cmd < file io linux","Size":42,"Id":"linux_28","HasId":true},{"CommandId":29,"Collection":"linux","Description":"Output of cmd2 as file input to cmd1","CommandText":"cmd1 <(cmd2)","Tags":[{"Name":"io"}],"CreatedAtUtc":"2024-02-21T22:47:40.5942905Z","SearchableText":"Output of cmd2 as file input to cmd1 cmd1 <(cmd2) io linux","Size":58,"Id":"linux_29","HasId":true},{"CommandId":30,"Collection":"linux","Description":"Standard output (stdout) of cmd to file","CommandText":"cmd > file","Tags":[{"Name":"io"}],"CreatedAtUtc":"2024-02-21T22:47:40.5942949Z","SearchableText":"Standard output (stdout) of cmd to file cmd > file io linux","Size":59,"Id":"linux_30","HasId":true},{"CommandId":31,"Collection":"linux","Description":"Discard stdout of cmd","CommandText":"cmd > /dev/null","Tags":[{"Name":"io"}],"CreatedAtUtc":"2024-02-21T22:47:40.5942967Z","SearchableText":"Discard stdout of cmd cmd > /dev/null io linux","Size":46,"Id":"linux_31","HasId":true},{"CommandId":32,"Collection":"linux","Description":"Append stdout to file","CommandText":"cmd >> file","Tags":[{"Name":"io"}],"CreatedAtUtc":"2024-02-21T22:47:40.5942985Z","SearchableText":"Append stdout to file cmd >> file io linux","Size":42,"Id":"linux_32","HasId":true},{"CommandId":33,"Collection":"linux","Description":"Error output (stderr) of cmd to file","CommandText":"cmd 2> file","Tags":[{"Name":"io"}],"CreatedAtUtc":"2024-02-21T22:47:40.5943005Z","SearchableText":"Error output (stderr) of cmd to file cmd 2> file io linux","Size":57,"Id":"linux_33","HasId":true},{"CommandId":34,"Collection":"linux","Description":"stdout to same place as stderr","CommandText":"cmd 1>&2","Tags":[{"Name":"io"}],"CreatedAtUtc":"2024-02-21T22:47:40.5943025Z","SearchableText":"stdout to same place as stderr cmd 1>&2 io linux","Size":48,"Id":"linux_34","HasId":true},{"CommandId":35,"Collection":"linux","Description":"stderr to same place as stdout","CommandText":"cmd 2>&1","Tags":[{"Name":"io"}],"CreatedAtUtc":"2024-02-21T22:47:40.5943044Z","SearchableText":"stderr to same place as stdout cmd 2>&1 io linux","Size":48,"Id":"linux_35","HasId":true},{"CommandId":36,"Collection":"linux","Description":"Every output of cmd to file","CommandText":"cmd &> file","Tags":[{"Name":"io"}],"CreatedAtUtc":"2024-02-21T22:47:40.5943062Z","SearchableText":"Every output of cmd to file cmd &> file io linux","Size":48,"Id":"linux_36","HasId":true},{"CommandId":37,"Collection":"linux","Description":"stdout of cmd1 to cmd2","CommandText":"cmd1 | cmd2","Tags":[{"Name":"pipes"}],"CreatedAtUtc":"2024-02-21T22:47:40.594308Z","SearchableText":"stdout of cmd1 to cmd2 cmd1 | cmd2 pipes linux","Size":46,"Id":"linux_37","HasId":true},{"CommandId":38,"Collection":"linux","Description":"stderr of cmd1 to cmd2","CommandText":"cmd1 |& cmd2","Tags":[{"Name":"pipes"}],"CreatedAtUtc":"2024-02-21T22:47:40.5943099Z","SearchableText":"stderr of cmd1 to cmd2 cmd1 |& cmd2 pipes linux","Size":47,"Id":"linux_38","HasId":true},{"CommandId":39,"Collection":"linux","Description":"Run cmd1 then cmd2","CommandText":"cmd1 ; cmd2","Tags":[{"Name":"command"}],"CreatedAtUtc":"2024-02-21T22:47:40.5943117Z","SearchableText":"Run cmd1 then cmd2 cmd1 ; cmd2 command linux","Size":44,"Id":"linux_39","HasId":true},{"CommandId":40,"Collection":"linux","Description":"Run cmd2 if cmd1 is successful","CommandText":"cmd1 && cmd2","Tags":[{"Name":"command"}],"CreatedAtUtc":"2024-02-21T22:47:40.5943137Z","SearchableText":"Run cmd2 if cmd1 is successful cmd1 && cmd2 command linux","Size":57,"Id":"linux_40","HasId":true},{"CommandId":41,"Collection":"linux","Description":"Run cmd2 if cmd1 is not successful","CommandText":"cmd1 || cmd2","Tags":[{"Name":"command"}],"CreatedAtUtc":"2024-02-21T22:47:40.5943157Z","SearchableText":"Run cmd2 if cmd1 is not successful cmd1 || cmd2 command linux","Size":61,"Id":"linux_41","HasId":true},{"CommandId":42,"Collection":"linux","Description":"Run cmd in a subshell","CommandText":"cmd &","Tags":[{"Name":"command"}],"CreatedAtUtc":"2024-02-21T22:47:40.5944248Z","SearchableText":"Run cmd in a subshell cmd & command linux","Size":41,"Id":"linux_42","HasId":true}]}